paymanai/__init__.py
paymanai/_base_client.py
paymanai/_client.py
paymanai/_compat.py
paymanai/_constants.py
paymanai/_exceptions.py
paymanai/_files.py
paymanai/_models.py
paymanai/_qs.py
paymanai/_resource.py
paymanai/_response.py
paymanai/_streaming.py
paymanai/_types.py
paymanai/_version.py
paymanai/py.typed
paymanai/_utils/__init__.py
paymanai/_utils/_logs.py
paymanai/_utils/_proxy.py
paymanai/_utils/_reflection.py
paymanai/_utils/_streams.py
paymanai/_utils/_sync.py
paymanai/_utils/_transform.py
paymanai/_utils/_typing.py
paymanai/_utils/_utils.py
paymanai/lib/.keep
paymanai/resources/__init__.py
paymanai/resources/balances.py
paymanai/resources/me.py
paymanai/resources/payments.py
paymanai/resources/spend_limits.py
paymanai/resources/version.py
paymanai/types/__init__.py
paymanai/types/balance_get_spendable_balance_response.py
paymanai/types/payment_create_payee_params.py
paymanai/types/payment_create_payee_response.py
paymanai/types/payment_delete_payee_response.py
paymanai/types/payment_search_payees_params.py
paymanai/types/payment_search_payees_response.py
paymanai/types/payment_send_payment_params.py
paymanai/types/payment_send_payment_response.py
paymanai-2.7.0.dist-info/METADATA
paymanai-2.7.0.dist-info/WHEEL
paymanai-2.7.0.dist-info/licenses/LICENSE
paymanai-2.7.0.dist-info/RECORD
